sc_supertree/__init__.py
sc_supertree/_app.py
sc_supertree/cli.py
sc_supertree/load.py
sc_supertree/py.typed
sc_supertree/scs.py
sc_supertree-2025.12.9.dist-info/entry_points.txt
sc_supertree-2025.12.9.dist-info/licenses/LICENSE
sc_supertree-2025.12.9.dist-info/WHEEL
sc_supertree-2025.12.9.dist-info/METADATA
sc_supertree-2025.12.9.dist-info/RECORD
