Metadata-Version: 2.4
Name: sc-supertree
Version: 2025.12.9
Summary: Spectral Cluster Supertree.
Keywords: supertree,phylogeny,biology,bioinformatics
Author: Robert McArthur
Requires-Python: >=3.12
Classifier: Development Status :: 5 - Production/Stable
Classifier: Intended Audience :: Science/Research
Classifier: License :: OSI Approved :: BSD License
Classifier: Topic :: Scientific/Engineering :: Bio-Informatics
Classifier: Topic :: Software Development :: Libraries :: Python Modules
Classifier: Operating System :: OS Independent
Classifier: Programming Language :: Python :: 3.12
Classifier: Programming Language :: Python :: 3.13
Classifier: Programming Language :: Python :: 3.14
License-File: LICENSE
Requires-Dist: click
Requires-Dist: numpy
Requires-Dist: cogent3>=2025.7.10a9
Requires-Dist: scikit-learn>=1.5.2
Requires-Dist: ruff==0.14.8 ; extra == "dev"
Requires-Dist: click==8.3.1 ; extra == "dev"
Requires-Dist: mypy==1.19.0 ; extra == "dev"
Requires-Dist: docformatter ; extra == "dev"
Requires-Dist: flit ; extra == "dev"
Requires-Dist: pytest ; extra == "dev"
Requires-Dist: pytest-cov ; extra == "dev"
Requires-Dist: pytest-xdist ; extra == "dev"
Requires-Dist: nox ; extra == "dev"
Requires-Dist: pytest ; extra == "test"
Requires-Dist: pytest-cov ; extra == "test"
Requires-Dist: pytest-xdist ; extra == "test"
Requires-Dist: nox ; extra == "test"
Project-URL: Bug Tracker, https://github.com/rmcar17/SpectralClusterSupertree/issues
Project-URL: Source Code, https://github.com/rmcar17/SpectralClusterSupertree
Provides-Extra: dev
Provides-Extra: test
